CowObfuscation/CowObfuscation.py
CowObfuscation/__init__.py
CowObfuscation/__version__.py
CowObfuscation-1.0.5.dist-info/METADATA
CowObfuscation-1.0.5.dist-info/WHEEL
CowObfuscation-1.0.5.dist-info/top_level.txt
CowObfuscation-1.0.5.dist-info/RECORD
